toolkit_bert_ner/__init__.py
toolkit_bert_ner/bert/__init__.py
toolkit_bert_ner/bert/create_pretraining_data.py
toolkit_bert_ner/bert/extract_features.py
toolkit_bert_ner/bert/modeling.py
toolkit_bert_ner/bert/modeling_test.py
toolkit_bert_ner/bert/optimization.py
toolkit_bert_ner/bert/optimization_test.py
toolkit_bert_ner/bert/run_classifier.py
toolkit_bert_ner/bert/run_pretraining.py
toolkit_bert_ner/bert/run_squad.py
toolkit_bert_ner/bert/tokenization.py
toolkit_bert_ner/bert/tokenization_test.py
toolkit_bert_ner/client/__init__.py
toolkit_bert_ner/runs/__init__.py
toolkit_bert_ner/server/__init__.py
toolkit_bert_ner/server/graph.py
toolkit_bert_ner/server/helper.py
toolkit_bert_ner/server/http.py
toolkit_bert_ner/server/zmq_decor.py
toolkit_bert_ner/train/__init__.py
toolkit_bert_ner/train/bert_lstm_ner.py
toolkit_bert_ner/train/conlleval.py
toolkit_bert_ner/train/lstm_crf_layer.py
toolkit_bert_ner/train/models.py
toolkit_bert_ner/train/tf_metrics.py
toolkit_bert_ner/train/train_helper.py
toolkit_bert_ner-1.0.2.dist-info/METADATA
toolkit_bert_ner-1.0.2.dist-info/WHEEL
toolkit_bert_ner-1.0.2.dist-info/entry_points.txt
toolkit_bert_ner-1.0.2.dist-info/top_level.txt
toolkit_bert_ner-1.0.2.dist-info/RECORD
