Metadata-Version: 2.1
Name: toolkit-bert-ner
Version: 1.0.2
Summary: Use Google's BERT for Chinese natural language processing tasks such as named entity recognition and provide server services
Home-page: https://github.com/wxl18039675170
Author: Allen WU
Author-email: allen.wu18621039969@gmail.com
License: MIT
Keywords: toolkit_bert_ner nlp ner NER named entity recognition bilstm crf tensorflow machine learning sentence encoding embedding serving
Platform: UNKNOWN
Classifier: Programming Language :: Python :: 3.4
Classifier: Programming Language :: Python :: 3.5
Classifier: Programming Language :: Python :: 3.6
Classifier: Programming Language :: Python :: 3.7
Classifier: License :: OSI Approved :: MIT License
Classifier: Operating System :: OS Independent
Requires-Dist: numpy
Requires-Dist: six
Requires-Dist: pyzmq (>=16.0.0)
Requires-Dist: GPUtil (>=1.3.0)
Requires-Dist: termcolor (>=1.1)
Provides-Extra: cpu
Requires-Dist: tensorflow (>=1.10.0) ; extra == 'cpu'
Provides-Extra: gpu
Requires-Dist: tensorflow-gpu (>=1.10.0) ; extra == 'gpu'
Provides-Extra: http
Requires-Dist: flask ; extra == 'http'
Requires-Dist: flask-compress ; extra == 'http'
Requires-Dist: flask-cors ; extra == 'http'
Requires-Dist: flask-json ; extra == 'http'
